codificador/codificador.vhd
library IEEE;
use IEEE.STD_LOGIC_1164.ALL;
use IEEE.STD_LOGIC_ARITH.ALL;
use IEEE.STD_LOGIC_UNSIGNED.ALL;
use ieee.numeric_std.all;


entity codificador is
generic (n: integer:=2); 
    Port ( entrada : in  STD_LOGIC_VECTOR ((2**n)-1 downto 0);
	      salida : out STD_LOGIC_VECTOR (n-1 downto 0));
end codificador;

architecture Behavioral of codificador is


begin


process (entrada)

begin

for i in 0 to (2**n)-1 loop

	if (entrada(i)='1') then
		salida<=std_logic_vector(to_unsigned(i,n)); 
	end if;

end loop;

end process;

end Behavioral;

codificador/codificador_tb.vhd
library IEEE;
use IEEE.STD_LOGIC_1164.ALL;
use IEEE.NUMERIC_STD.ALL; 
 
ENTITY codificador_tb IS
generic (n: integer := 3); -- Definimos n=3 para 8 entradas
END codificador_tb;
 
ARCHITECTURE behavior OF codificador_tb IS 
 
   COMPONENT codificador
    generic (n: integer := 3); -- Aseguramos coincidencia con el testbench
    Port ( 
      entrada : in  STD_LOGIC_VECTOR ((2**n)-1 downto 0);
      salida : out STD_LOGIC_VECTOR (n-1 downto 0)
    );
   END COMPONENT;

   -- Señales de prueba
   signal entrada : std_logic_vector((2**n)-1 downto 0) := (others => '0');
   signal salida : std_logic_vector(n-1 downto 0);
 
BEGIN
   -- Instancia del componente bajo prueba
   uut: codificador 
     generic map(n => 3) -- Especificamos n=3 aquí también
     PORT MAP (
       entrada => entrada,
       salida => salida
     );

   -- Proceso de estimulación
   stim_proc: process
   begin
      report "Iniciando simulacion...";
      
      -- Prueba 1: Ninguna entrada activa
      entrada <= (others => '0');
      wait for 100 ns;
      assert salida = "000" report "Error en caso 00000000" severity error;
      
      -- Prueba 2: Activamos cada entrada individualmente
      for i in 0 to (2**n)-1 loop
        entrada <= (others => '0');
        entrada(i) <= '1';
        wait for 100 ns;
        assert salida = std_logic_vector(to_unsigned(i, n)) 
          report "Error en entrada " & integer'image(i) severity error;
      end loop;
      
      -- Prueba 3: Múltiples entradas activas (verificamos prioridad)
      entrada <= "00000001"; wait for 50 ns;
      assert salida = "000" report "Error prioridad 0" severity error;
      
      entrada <= "00000011"; wait for 50 ns;
      assert salida = "001" report "Error prioridad 1" severity error;
      
      entrada <= "00001111"; wait for 50 ns;
      assert salida = "011" report "Error prioridad 3" severity error;
      
      entrada <= "11111111"; wait for 50 ns;
      assert salida = "111" report "Error prioridad 7" severity error;
      
      -- Prueba 4: Patrones aleatorios
      entrada <= "01010101"; wait for 50 ns;
      assert salida = "110" report "Error patron 01010101" severity error;
      
      entrada <= "00110011"; wait for 50 ns;
      assert salida = "101" report "Error patron 00110011" severity error;
      
      report "Simulacion completada";
      wait;
   end process;

END;

codificador/codificador.vcd
$date
  Tue Apr  1 18:01:32 2025
$end
$version
  GHDL v0
$end
$timescale
  1 fs
$end
$scope module standard $end
$upscope $end
$scope module std_logic_1164 $end
$upscope $end
$scope module numeric_std $end
$upscope $end
$scope module codificador_tb $end
$var reg 8 ! entrada[7:0] $end
$var reg 3 " salida[2:0] $end
$scope module uut $end
$var reg 8 # entrada[7:0] $end
$var reg 3 $ salida[2:0] $end
$upscope $end
$upscope $end
$enddefinitions $end
#0
b00000000 !
b000 "
b00000000 #
b000 $
#100000000
b00000001 !
b00000001 #
#200000000
b00000010 !
b001 "
b00000010 #
b001 $
#300000000
b00000100 !
b010 "
b00000100 #
b010 $
#400000000
b00001000 !
b011 "
b00001000 #
b011 $
#500000000
b00010000 !
b100 "
b00010000 #
b100 $
#600000000
b00100000 !
b101 "
b00100000 #
b101 $
#700000000
b01000000 !
b110 "
b01000000 #
b110 $
#800000000
b10000000 !
b111 "
b10000000 #
b111 $
#900000000
b00000001 !
b000 "
b00000001 #
b000 $
#950000000
b00000011 !
b001 "
b00000011 #
b001 $
#1000000000
b00001111 !
b011 "
b00001111 #
b011 $
