biestablejk_asincrono/biestablejk_asincrono.vhd
library IEEE;
use IEEE.STD_LOGIC_1164.ALL;


entity biestablejk_asincrono is
    Port ( J : in  STD_LOGIC;
		 K : in STD_LOGIC;
           clk : in  STD_LOGIC;
           reset : in  STD_LOGIC;
           Q : out  STD_LOGIC);
end biestablejk_asincrono;

architecture Behavioral of biestablejk_asincrono is

signal dato: std_logic;

begin

process(clk)

begin

	if (reset='1') then  

	dato<='0';
	elsif (rising_edge(clk)) then
		if (J='0' and K='0') then
		dato<=dato;
		elsif (J='0' and K='1') then
		dato<='0';
		elsif (J='1' and K='0') then
		dato<='1';
		else
		dato<=not(dato);
		end if;
	end if;
	
	
end process;
Q<=dato;
end Behavioral;

biestablejk_asincrono_tb.vhd
--------------------------------------------------------------------------------
-- Descripción VHDL parametrizable del test de prueba para el bloque biestable JK asíncrono

-- Desarrollado por Irene Bujalance Fernández
--------------------------------------------------------------------------------

LIBRARY ieee;
USE ieee.std_logic_1164.ALL;
 
 
ENTITY biestablejk_asincrono_tb IS
END biestablejk_asincrono_tb;
 
ARCHITECTURE behavior OF biestablejk_asincrono_tb IS 
  
    COMPONENT biestablejk_asincrono
    PORT(
         J : IN  std_logic;
			K : IN std_logic;
         clk : IN  std_logic;
         reset : IN  std_logic;
         Q : OUT  std_logic
        );
    END COMPONENT;
    

   signal J : std_logic := '0';
	signal K : std_logic := '0';
   signal clk : std_logic := '0';
   signal reset : std_logic := '0';

    signal Q : std_logic;

    
BEGIN
 
	   uut: biestablejk_asincrono PORT MAP (
          J => J,
	     K=> K,
          clk => clk,
          reset => reset,
          Q => Q
        );

   clk_process :process
   begin
	clk <= '0';
	wait for 50 ns;
	clk <= '1';
	wait for 50 ns;
	end process;

 

   stim_proc: process
   begin		
     J<='0';K<='0';reset<='1';
     wait for 150 ns;	
	reset<='0';
	wait for 100 ns;	
	J<='0';K<='1';
	wait for 100 ns;
	J<='1';k<='0';
	wait for 100 ns;
	J<='1';K<='1';
	wait for 100 ns;
     wait;
   end process;

END;

biestablejk_asincrono/biestablejk_asincrono.vcd
$date
  Tue Apr  1 12:50:57 2025
$end
$version
  GHDL v0
$end
$timescale
  1 fs
$end
$scope module standard $end
$upscope $end
$scope module std_logic_1164 $end
$upscope $end
$scope module biestablejk_asincrono_tb $end
$var reg 1 ! j $end
$var reg 1 " k $end
$var reg 1 # clk $end
$var reg 1 $ reset $end
$var reg 1 % q $end
$scope module uut $end
$var reg 1 & j $end
$var reg 1 ' k $end
$var reg 1 ( clk $end
$var reg 1 ) reset $end
$var reg 1 * q $end
$var reg 1 + dato $end
$upscope $end
$upscope $end
$enddefinitions $end
#0
0!
0"
0#
1$
U%
0&
0'
0(
1)
U*
U+
#50000000
1#
0%
1(
0*
0+
#100000000
0#
0(
#150000000
1#
0$
1(
0)
#200000000
0#
0(
#250000000
1"
1#
1'
1(
#300000000
0#
0(
#350000000
1!
0"
1#
1%
1&
0'
1(
1*
1+
#400000000
0#
0(
#450000000
1"
1#
0%
1'
1(
0*
0+
#500000000
0#
0(
#550000000
1#
1%
1(
1*
1+
#600000000
0#
0(
#650000000
1#
0%
1(
0*
0+
#700000000
0#
0(
#750000000
1#
1%
1(
1*
1+
#800000000
0#
0(
#850000000
1#
0%
1(
0*
0+
#900000000
0#
0(
#950000000
1#
1%
1(
1*
1+
