contador/contador.vhd
library IEEE;
use IEEE.STD_LOGIC_1164.ALL;
USE IEEE.NUMERIC_STD.ALL;
USE IEEE.STD_LOGIC_ARITH.ALL;
USE IEEE.STD_LOGIC_UNSIGNED.ALL;



entity contador is
	generic (n: integer:=3); 
    Port ( en : in  STD_LOGIC;
		direccion: in std_logic; 
           reset : in  STD_LOGIC;
           clk : in  STD_LOGIC;
           cuenta : out  STD_LOGIC_VECTOR (n-1 downto 0));
end contador;

architecture Behavioral of contador is

signal cont:std_logic_vector(n-1 downto 0);

begin

process(clk,reset)

begin
	if (reset='1') then
	cont<=std_logic_vector(to_unsigned(0,n));
	elsif (rising_edge(clk)) then
		if (en='1') then
			if (direccion='0') then
			cont<=cont + '1';
			else cont<=cont-'1';
			end if;
		else
		cont<=cont;
		end if;
	end if;

end process;

cuenta<=cont;

end Behavioral;

contador/contador_tb.vhd
LIBRARY ieee;
USE ieee.std_logic_1164.ALL;
  
ENTITY contador_tb IS
generic (n: integer:=4);
END contador_tb;
 
ARCHITECTURE behavior OF contador_tb IS 
 
     
    COMPONENT contador
	 generic (n: integer:=3);
    PORT(
         en : IN  std_logic;
	    direccion: IN std_logic;
         reset : IN  std_logic;
         clk : IN  std_logic;
         cuenta : OUT  std_logic_vector(n-1 downto 0)
        );
    END COMPONENT;
    

   signal en : std_logic := '0';
   signal direccion: std_logic := '0';
   signal reset : std_logic := '0';
   signal clk : std_logic := '0';

   signal cuenta : std_logic_vector(n-1 downto 0);

 
BEGIN
 
	uut: contador 
	generic map(n=>4)
	PORT MAP (
          en => en,
	     direccion => direccion,
          reset => reset,
          clk => clk,
          cuenta => cuenta
        );

   clk_process :process
   begin
		clk <= '0';
		wait for 50 ns;
		clk <= '1';
		wait for 50 ns;
   end process;
 

   
   stim_proc: process
   begin		
      reset<='1';en<='0';direccion<='0';
      wait for 100 ns;	
	 reset<='0';
      wait for 100 ns;
	 en<='1';
      wait for 400 ns; 
	 direccion<='1';
	 wait for 400 ns;

      wait;
   end process;

END;

contador/contador.vcd
$date
  Tue Apr  1 18:29:59 2025
$end
$version
  GHDL v0
$end
$timescale
  1 fs
$end
$scope module standard $end
$upscope $end
$scope module std_logic_1164 $end
$upscope $end
$scope module numeric_std $end
$upscope $end
$scope module std_logic_arith $end
$upscope $end
$scope module std_logic_unsigned $end
$upscope $end
$scope module contador_tb $end
$var reg 1 ! en $end
$var reg 1 " direccion $end
$var reg 1 # reset $end
$var reg 1 $ clk $end
$var reg 4 % cuenta[3:0] $end
$scope module uut $end
$var reg 1 & en $end
$var reg 1 ' direccion $end
$var reg 1 ( reset $end
$var reg 1 ) clk $end
$var reg 4 * cuenta[3:0] $end
$var reg 4 + cont[3:0] $end
$upscope $end
$upscope $end
$enddefinitions $end
#0
0!
0"
1#
0$
b0000 %
0&
0'
1(
0)
b0000 *
b0000 +
#50000000
1$
1)
#100000000
0#
0$
0(
0)
#150000000
1$
1)
#200000000
1!
0$
1&
0)
#250000000
1$
b0001 %
1)
b0001 *
b0001 +
#300000000
0$
0)
#350000000
1$
b0010 %
1)
b0010 *
b0010 +
#400000000
0$
0)
#450000000
1$
b0011 %
1)
b0011 *
b0011 +
#500000000
0$
0)
#550000000
1$
b0100 %
1)
b0100 *
b0100 +
#600000000
1"
0$
1'
0)
#650000000
1$
b0011 %
1)
b0011 *
b0011 +
#700000000
0$
0)
#750000000
1$
b0010 %
1)
b0010 *
b0010 +
#800000000
0$
0)
#850000000
1$
b0001 %
1)
b0001 *
b0001 +
#900000000
0$
0)
#950000000
1$
b0000 %
1)
b0000 *
b0000 +
